odysseyz_ovkitmcp/__init__.py
odysseyz_ovkitmcp-0.1.0.dist-info/METADATA
odysseyz_ovkitmcp-0.1.0.dist-info/WHEEL
odysseyz_ovkitmcp-0.1.0.dist-info/entry_points.txt
odysseyz_ovkitmcp-0.1.0.dist-info/RECORD
